PyDataCraft/__init__.py
PyDataCraft/__main__.py
PyDataCraft/DATA/LOGO.gif
PyDataCraft-0.4.dist-info/METADATA
PyDataCraft-0.4.dist-info/WHEEL
PyDataCraft-0.4.dist-info/entry_points.txt
PyDataCraft-0.4.dist-info/top_level.txt
PyDataCraft-0.4.dist-info/RECORD
